{
  "id": 20,
  "title": "Себежский национальный парк",
  "category": ["nature", "eco", "outdoor"],
  "distance": "7.5 км",
  "duration": "4–5 часов",
  "difficulty": "Средняя",
  "type": "Пешеходный",
  "description": "Экологический маршрут по озёрно-лесному ландшафту национального парка.",
  "image": "sebezh",
  "color": "#2E8B57",
  "howToGet": "Начало — визит-центр национального парка.",
  "tips": "Посещение по правилам ООПТ.",
  "points": [
    {
      "coords": [56.286914, 28.482173],
      "title": "Визит-центр парка",
      "description": "Информационная точка с картами маршрутов.",
      "activity": "Уточните состояние троп.",
      "emotion": "Подготовка",
      "icon": "fa-info-circle",
      "type": "start",
      "geoAccuracy": "exact"
    },
    {
      "coords": [56.289742, 28.486512],
      "title": "Лесная экотропа",
      "description": "Маркированный маршрут через смешанный лес.",
      "activity": "Следуйте указателям.",
      "emotion": "Погружение",
      "icon": "fa-tree",
      "type": "eco",
      "geoAccuracy": "exact"
    },
    {
      "coords": [56.292418, 28.490327],
      "title": "Смотровая точка у озера",
      "description": "Выход к воде с обзором береговой линии.",
      "activity": "Наблюдение за птицами.",
      "emotion": "Тишина",
      "icon": "fa-binoculars",
      "type": "view",
      "geoAccuracy": "exact"
    }
  ]
}
